{"title": "Make Developers Autonomous With Kafka Self-Service Tools", "author": "James White", "url": "https://thenewstack.io/make-developers-autonomous-with-kafka-self-service-tools/", "hostname": "thenewstack.io", "description": "Improve development team autonomy by giving them the right tools to self-service their Kafka data, security and access requirements.", "sitename": "The New Stack", "date": "2024-06-21", "categories": ["Data", "Data Streaming", "DevOps"], "tags": [], "fingerprint": null, "id": null, "license": null, "body": null, "comments": null, "commentsbody": null, "raw_text": null, "text": null, "language": null, "image": "https://cdn.thenewstack.io/media/2024/06/21407506-make-developers-autonomous-kafka-self-service-tools.png", "pagetype": "article", "cntitle": "\u4f7f\u7528 Kafka \u81ea\u52a9\u670d\u52a1\u5de5\u5177\u8ba9\u5f00\u53d1\u4eba\u5458\u81ea\u4e3b", "cndescription": "\u901a\u8fc7\u4e3a\u5f00\u53d1\u56e2\u961f\u63d0\u4f9b\u5408\u9002\u7684\u5de5\u5177\u6765\u81ea\u52a9\u670d\u52a1\u5176 Kafka \u6570\u636e\u3001\u5b89\u5168\u548c\u8bbf\u95ee\u9700\u6c42\uff0c\u63d0\u9ad8\u5f00\u53d1\u56e2\u961f\u7684\u81ea\u4e3b\u6027\u3002"}