{"title": "40% of Companies Will Use AI to 'Interview' Job Applicants, Report", "author": "Vinay Patel", "url": "https://www.ibtimes.co.uk/40-companies-will-use-ai-interview-job-applicants-report-1723901", "hostname": "ibtimes.co.uk", "description": "While both employers and candidates benefit from AI tools, concerns linger about bias and impersonal AI interviews.", "sitename": "International Business Times UK", "date": "2024-04-03", "categories": ["Companies"], "tags": ["Artificial Intelligence", "Artificial Intelligence (AI)", "jobs", "jobs and AI"], "fingerprint": null, "id": null, "license": null, "body": null, "comments": null, "commentsbody": null, "raw_text": null, "text": null, "language": null, "image": "https://d.ibtimes.co.uk/en/full/1723454/ai-used-candidate-hiring-process.jpg", "pagetype": "article", "cntitle": "40% \u7684\u516c\u53f8\u5c06\u4f7f\u7528\u4eba\u5de5\u667a\u80fd\u6765\u201c\u9762\u8bd5\u201d\u6c42\u804c\u8005\uff0c\u62a5\u544a", "cndescription": "\u867d\u7136\u96c7\u4e3b\u548c\u5019\u9009\u4eba\u90fd\u53d7\u76ca\u4e8e\u4eba\u5de5\u667a\u80fd\u5de5\u5177\uff0c\u4f46\u4eba\u4eec\u4ecd\u7136\u62c5\u5fc3\u504f\u89c1\u548c\u975e\u4e2a\u4eba\u5316\u7684\u4eba\u5de5\u667a\u80fd\u9762\u8bd5\u3002"}