{"title": "How the CSI (Container Storage Interface) Works", "author": "Steven Sklar Guest Author; QuestDB", "url": "https://www.simplyblock.io/post/how-the-csi-container-storage-interface-works", "hostname": "simplyblock.io", "description": "A deep dive into what the CSI (Container Storage Interface) is and how it works in Kubernetes (k8s).", "sitename": "simplyblock.io", "date": "2024-03-29", "categories": [], "tags": [], "fingerprint": null, "id": null, "license": null, "body": null, "comments": null, "commentsbody": null, "raw_text": null, "text": null, "language": null, "image": "https://static.wixstatic.com/media/a7fbb2_2a8fd8f55d654398b98b33568927746f~mv2.jpg/v1/fill/w_1200,h_627,al_c/a7fbb2_2a8fd8f55d654398b98b33568927746f~mv2.jpg", "pagetype": "article", "cntitle": "CSI\uff08\u5bb9\u5668\u5b58\u50a8\u63a5\u53e3\uff09\u7684\u5de5\u4f5c\u539f\u7406", "cndescription": "\u6df1\u5165\u4e86\u89e3 CSI\uff08\u5bb9\u5668\u5b58\u50a8\u63a5\u53e3\uff09\u662f\u4ec0\u4e48\u4ee5\u53ca\u5b83\u5982\u4f55\u5728 Kubernetes\uff08k8s\uff09\u4e2d\u5de5\u4f5c\u3002"}