{"title": "From Netflix to Walmart: Open Source Kafka in Action", "author": "Varun Ghai", "url": "https://thenewstack.io/from-netflix-to-walmart-open-source-kafka-in-action/", "hostname": "thenewstack.io", "description": "These case studies show four critical areas where Kafka excels: real-time data processing, messaging, operational metrics and log aggregation.", "sitename": "The New Stack", "date": "2025-03-04", "categories": ["Data", "Data Streaming"], "tags": [], "fingerprint": null, "id": null, "license": null, "body": null, "comments": null, "commentsbody": null, "raw_text": null, "text": null, "language": null, "image": "https://cdn.thenewstack.io/media/2025/03/cfcef75f-open-source-kafka-in-action.jpg", "pagetype": "article", "filedate": "2025-03-05", "cntitle": "\u4ece Netflix \u5230 Walmart\uff1a\u5f00\u6e90 Kafka \u7684\u5b9e\u9645\u5e94\u7528", "cndescription": "\u4ee5\u4e0b\u6848\u4f8b\u7814\u7a76\u5c55\u793a\u4e86 Kafka \u5728\u56db\u4e2a\u5173\u952e\u9886\u57df\u7684\u5353\u8d8a\u8868\u73b0\uff1a\u5b9e\u65f6\u6570\u636e\u5904\u7406\u3001\u6d88\u606f\u4f20\u9012\u3001\u8fd0\u8425\u6307\u6807\u548c\u65e5\u5fd7\u805a\u5408\u3002"}