{"title": "7 Tips for Fostering Stronger Communication in Outsourced Projects", "author": "Liz Ryan", "url": "https://thenewstack.io/7-tips-for-fostering-stronger-communication-in-outsourced-projects/", "hostname": "thenewstack.io", "description": "Could better communication have prevented problems and hurdles in your outsourced project? Most likely.", "sitename": "The New Stack", "date": "2024-05-02", "categories": ["DevOps", "Tech Culture"], "tags": [], "fingerprint": null, "id": null, "license": null, "body": null, "comments": null, "commentsbody": null, "raw_text": null, "text": null, "language": null, "image": "https://cdn.thenewstack.io/media/2024/04/0dbde33e-planning.jpg", "pagetype": "article", "cntitle": "\u5916\u5305\u9879\u76ee\u4e2d\u52a0\u5f3a\u6c9f\u901a\u7684 7 \u4e2a\u6280\u5de7", "cndescription": "\u66f4\u597d\u7684\u6c9f\u901a\u662f\u5426\u53ef\u4ee5\u907f\u514d\u5916\u5305\u9879\u76ee\u4e2d\u7684\u95ee\u9898\u548c\u969c\u788d\uff1f\u5f88\u6709\u53ef\u80fd\u3002"}