{"title": "MongoDB 8 Goes Hard on Time-Series Data, Horizontal Scaling", "author": "Joab Jackson", "url": "https://thenewstack.io/mongodb-8-goes-hard-on-time-series-data-horizontal-scaling/", "hostname": "thenewstack.io", "description": "Optimizations have made the database system 32% more performant. Time-series aggregations have boosted performance by 200%, and scalability has been improved by 50%.", "sitename": "The New Stack", "date": "2024-10-02", "categories": ["Databases"], "tags": [], "fingerprint": null, "id": null, "license": null, "body": null, "comments": null, "commentsbody": null, "raw_text": null, "text": null, "language": null, "image": "https://cdn.thenewstack.io/media/2024/10/5d6d4528-mongodb.png", "pagetype": "article", "filedate": "2024-10-06", "cntitle": "MongoDB 8 \u4e13\u6ce8\u4e8e\u65f6\u95f4\u5e8f\u5217\u6570\u636e\u548c\u6a2a\u5411\u6269\u5c55", "cndescription": "\u4f18\u5316\u4f7f\u6570\u636e\u5e93\u7cfb\u7edf\u6027\u80fd\u63d0\u9ad8\u4e86 32%\u3002\u65f6\u95f4\u5e8f\u5217\u805a\u5408\u4f7f\u6027\u80fd\u63d0\u9ad8\u4e86 200%\uff0c\u53ef\u6269\u5c55\u6027\u63d0\u9ad8\u4e86 50%\u3002"}