{"title": "Python Developers Hold the Key to Blockchain Adoption", "author": "John Woods", "url": "https://thenewstack.io/python-developers-hold-the-key-to-blockchain-adoption/", "hostname": "thenewstack.io", "description": "You don't need to know a niche language or have specialist skills in cryptography to participate; you just need Python.", "sitename": "The New Stack", "date": "2024-07-10", "categories": ["Python", "Software Development"], "tags": [], "fingerprint": null, "id": null, "license": null, "body": null, "comments": null, "commentsbody": null, "raw_text": null, "text": null, "language": null, "image": "https://cdn.thenewstack.io/media/2024/07/a6a7557e-eye-2005639_1280.jpg", "pagetype": "article", "filedate": "2024-07-11", "cntitle": "Python \u5f00\u53d1\u8005\u662f\u533a\u5757\u94fe\u91c7\u7528\u7684\u5173\u952e", "cndescription": "\u60a8\u4e0d\u9700\u8981\u4e86\u89e3\u5c0f\u4f17\u8bed\u8a00\u6216\u62e5\u6709\u5bc6\u7801\u5b66\u7684\u4e13\u4e1a\u6280\u80fd\u5373\u53ef\u53c2\u4e0e\uff1b\u60a8\u53ea\u9700\u8981 Python\u3002"}