{"title": "When You Don't Need GPUs to Run AI: A 'Farm Fresh' Case Study", "author": "Joab Jackson", "url": "https://thenewstack.io/when-you-dont-need-gpus-to-run-ai-a-farm-fresh-case-study/", "hostname": "thenewstack.io", "description": "How the latest generation of Intel AMX-enabled Xeon processors can power many AI jobs that previously could only be done with GPUs.", "sitename": "The New Stack", "date": "2024-09-07", "categories": ["AI", "Hardware", "Operations"], "tags": ["Earl Ruby"], "fingerprint": null, "id": null, "license": null, "body": null, "comments": null, "commentsbody": null, "raw_text": null, "text": null, "language": null, "image": "https://cdn.thenewstack.io/media/2024/09/37fe0ae7-vmware-explore-ruby-bradley.jpg", "pagetype": "article", "filedate": "2024-09-08", "cntitle": "\u65e0\u9700 GPU \u8fd0\u884c AI \u7684\u60c5\u51b5\uff1a\u4e00\u4e2a\u201c\u519c\u573a\u65b0\u9c9c\u201d\u6848\u4f8b\u7814\u7a76", "cndescription": "\u6700\u65b0\u4e00\u4ee3\u652f\u6301\u82f1\u7279\u5c14 AMX \u7684\u81f3\u5f3a\u5904\u7406\u5668\u5982\u4f55\u4e3a\u8bb8\u591a\u4ee5\u524d\u53ea\u80fd\u7528 GPU \u5b8c\u6210\u7684 AI \u4efb\u52a1\u63d0\u4f9b\u52a8\u529b\u3002"}