{"title": "Contract-as-Code: Why Finance Teams Are Taking Over Your API Contracts", "author": "Matt Lhoumeau", "url": "https://thenewstack.io/contract-as-code-why-finance-teams-are-taking-over-your-api-contracts/", "hostname": "thenewstack.io", "description": "DevOps teams face growing friction from outdated contract workflows.", "sitename": "The New Stack", "date": "2025-04-19", "categories": ["AI", "Cloud Native Ecosystem", "DevOps"], "tags": [], "fingerprint": null, "id": null, "license": null, "body": null, "comments": null, "commentsbody": null, "raw_text": null, "text": null, "language": null, "image": "https://cdn.thenewstack.io/media/2025/04/ba305032-hands-2088954_1280.jpg", "pagetype": "article", "filedate": "2025-04-20", "cntitle": "\u5408\u7ea6\u5373\u4ee3\u7801\uff1a\u4e3a\u4ec0\u4e48\u8d22\u52a1\u56e2\u961f\u6b63\u5728\u63a5\u7ba1\u4f60\u7684 API \u5408\u7ea6", "cndescription": "DevOps \u56e2\u961f\u6b63\u9762\u4e34\u7740\u56e0\u8fc7\u65f6\u7684\u5408\u540c\u5de5\u4f5c\u6d41\u7a0b\u800c\u65e5\u76ca\u589e\u957f\u7684\u6469\u64e6\u3002"}