{"title": "Protobom: Paving the Path for SBOM Adoption", "author": "Jeffrey Burt", "url": "https://thenewstack.io/protobom-paving-the-path-for-sbom-adoption/", "hostname": "thenewstack.io", "description": "CISA, DHS, and OpenSSF are introducing Protobom, an open source tool they say will make it easier for enterprises protect their software supply chains.", "sitename": "The New Stack", "date": "2024-04-18", "categories": ["Open Source", "Security"], "tags": [], "fingerprint": null, "id": null, "license": null, "body": null, "comments": null, "commentsbody": null, "raw_text": null, "text": null, "language": null, "image": "https://cdn.thenewstack.io/media/2024/04/36d606ce-lili-popper-lu15z1m_kfm-unsplash-1.jpg", "pagetype": "article", "cntitle": "Protobom\uff1a\u4e3a SBOM \u91c7\u7528\u94fa\u5e73\u9053\u8def", "cndescription": "CISA\u3001DHS \u548c OpenSSF \u6b63\u5728\u63a8\u51fa Protobom\uff0c\u4ed6\u4eec\u8868\u793a\uff0c\u8fd9\u662f\u4e00\u4e2a\u5f00\u6e90\u5de5\u5177\uff0c\u5c06\u4f7f\u4f01\u4e1a\u66f4\u5bb9\u6613\u4fdd\u62a4\u5176\u8f6f\u4ef6\u4f9b\u5e94\u94fe\u3002"}