{"url":"https://thenewstack.io/googles-web-ai-playbook-the-paved-road-vs-the-open-field/","title":"Google’s Web AI Playbook: The Paved Road vs. the Open Field","author":"Richard MacManus","summary":"","cover":"https://cdn.thenewstack.io/media/2025/11/6c1a87bd-getty-images-e3gjtedeeoi-unsplashb.jpg","zh_title":"谷歌AI创业“路线图”：坦途还是荒野？","zh_summary":"Google 在 Web AI 峰会上强调浏览器端 AI 的发展，推出 WebMCP、WebGPU 等技术，旨在普及 AI。Parisa Tabriz 将此视为“Web 的文艺复兴”。Google 致力于开放 Web，并预测浏览器将成为生产力平台。Kenji Baheux 介绍了两种开发模式：便捷的“铺好的道路”和灵活的“开放领域”。"}